README
setup.py
pynetviz/__init__.py
pynetviz/linkurious.py
pynetviz/sigmajs.py
pynetviz.egg-info/PKG-INFO
pynetviz.egg-info/SOURCES.txt
pynetviz.egg-info/dependency_links.txt
pynetviz.egg-info/requires.txt
pynetviz.egg-info/top_level.txt