Metadata-Version: 1.1
Name: pynetviz
Version: 0.1
Summary: Python Network(Graph) Visualization
Home-page: https://github.com/koorukuroo/pynetviz
Author: Kyunghoon Kim
Author-email: kyunghoon@unist.ac.kr
License: MIT License
Keywords: Network,Graph,Visualization
Platform: UNKNOWN
Classifier: Programming Language :: Python
Classifier: License :: OSI Approved :: MIT License
Classifier: Topic :: Software Development :: Libraries :: Python Modules
Classifier: Topic :: Scientific/Engineering :: Visualization
